atlaselectrophysiology/AdaptedAxisItem.py
atlaselectrophysiology/ColorBar.py
atlaselectrophysiology/__init__.py
atlaselectrophysiology/alignment_with_easyqc.py
atlaselectrophysiology/compare_alignments.py
atlaselectrophysiology/create_overview_plots.py
atlaselectrophysiology/ephys_atlas_gui.py
atlaselectrophysiology/ephys_gui_setup.py
atlaselectrophysiology/example_code.py
atlaselectrophysiology/extract_files.py
atlaselectrophysiology/get_scale_factor.py
atlaselectrophysiology/load_data.py
atlaselectrophysiology/load_data_local.py
atlaselectrophysiology/load_histology.py
atlaselectrophysiology/plot_data.py
atlaselectrophysiology/qc_table.py
atlaselectrophysiology/rendering.py
atlaselectrophysiology/sandbox.py
atlasview/__init__.py
atlasview/atlasview.py
atlasview/launcher.py
dlc/DLC_labeled_video.py
dlc/__init__.py
dlc/get_dlc_traces.py
dlc/overview_plot_dlc.py
dlc/stream_dlc_labeled_frames.py
dlc/wheel_dlc_viewer.py
histology/__init__.py
histology/atlas_mpl.py
histology/transform-tracks.py
task_qc_viewer/ViewEphysQC.py
task_qc_viewer/__init__.py
task_qc_viewer/task_qc.py
task_qc_viewer/version.py
tests/__init__.py
tests/test_alignment_qc_gui.py
tests/test_task_qc_viewer.py
iblapps-0.0.1.dist-info/LICENSE
iblapps-0.0.1.dist-info/METADATA
iblapps-0.0.1.dist-info/WHEEL
iblapps-0.0.1.dist-info/top_level.txt
iblapps-0.0.1.dist-info/RECORD
