Metadata-Version: 2.1
Name: iblapps
Version: 0.0.1
Summary: IBL Applications
Home-page: https://www.internationalbrainlab.com/
Author: IBL Staff
License: MIT
Platform: UNKNOWN
Requires-Python: >=3.8
License-File: LICENSE
Requires-Dist: easyqc
Requires-Dist: ibllib
Requires-Dist: PyQt5
Requires-Dist: pyqtgraph
Requires-Dist: simpleITK
